[
  {
    "date": "13/01/2024",
    "time": "01:02:10",
    "username": "lakatastrauf",
    "message": "Comment ils ont su ?",
    "isMod": false,
    "isVIP": false
  },
  {
    "date": "13/01/2024",
    "time": "01:03:53",
    "username": "wizebot",
    "message": "⭐️ RE-SUB ⭐️ KGeKraa (+1) ⭐️",
    "isMod": true,
    "isVIP": false
  },
  {
    "date": "13/01/2024",
    "time": "01:03:58",
    "username": "kgekraa",
    "message": "ouais ouais ouais",
    "isMod": true,
    "isVIP": false
  },
  {
    "date": "13/01/2024",
    "time": "01:04:00",
    "username": "mohaonthefire",
    "message": "JE TAIME RISES TU LE SAIS COMME TT LES JOURS",
    "isMod": false,
    "isVIP": false
  },
  {
    "date": "13/01/2024",
    "time": "01:04:17",
    "username": "kgekraa",
    "message": "730 sub ?????",
    "isMod": true,
    "isVIP": false
  },
  {
    "date": "13/01/2024",
    "time": "01:04:30",
    "username": "kgekraa",
    "message": "y a eu autant de sub la dernière fois ptdr",
    "isMod": true,
    "isVIP": false
  },
  {
    "date": "13/01/2024",
    "time": "01:04:35",
    "username": "mohaonthefire",
    "message": "C FIVEM",
    "isMod": false,
    "isVIP": false
  },
  {
    "date": "13/01/2024",
    "time": "01:04:37",
    "username": "mohaonthefire",
    "message": "JE CROIS",
    "isMod": false,
    "isVIP": false
  },
  {
    "date": "13/01/2024",
    "time": "01:04:53",
    "username": "fda_delta",
    "message": "masterclass",
    "isMod": false,
    "isVIP": false
  },
  {
    "date": "13/01/2024",
    "time": "01:04:58",
    "username": "kgekraa",
    "message": "rah ouais il va manger des cailloux avec de la sauce le mois prochain mdr",
    "isMod": true,
    "isVIP": false
  },
  {
    "date": "13/01/2024",
    "time": "01:07:00",
    "username": "x_ash0",
    "message": "les frères vous avez le twitch de makhila le hoover ?",
    "isMod": false,
    "isVIP": false
  },
  {
    "date": "13/01/2024",
    "time": "01:08:15",
    "username": "kgekraa",
    "message": "@x_ash0 cherche par toi même t’es chez rises ici",
    "isMod": true,
    "isVIP": false
  },
  {
    "date": "13/01/2024",
    "time": "01:08:36",
    "username": "kgekraa",
    "message": "@x_ash0 prochaine fois c’est sanction",
    "isMod": true,
    "isVIP": false
  },
  {
    "date": "13/01/2024",
    "time": "01:08:39",
    "username": "lecaennais14",
    "message": "!projet",
    "isMod": true,
    "isVIP": false
  },
  {
    "date": "13/01/2024",
    "time": "01:08:39",
    "username": "streamelements",
    "message": "Début du projet Puente 13 ! Il est composé de : Gykows, Cjane, Shayou, Darkfuneral, Jaybee, Lz_Haamaa, JlClaow, Samiaalpha, ViggyNight, Lz_Rises, Miidouw, Nastya, Mrbboy, Tobias, SomSammm",
    "isMod": true,
    "isVIP": false
  },
  {
    "date": "13/01/2024",
    "time": "01:08:39",
    "username": "wizebot",
    "message": "Début du projet Puente 13 ! Il est composé de : Gykows, Cjane, Shayou, Darkfuneral, Jaybee, Lz_Haamaa, JlClaow, Samiaalpha, ViggyNight, Lz_Rises, Miidouw, Nastya, Mrbboy, Tobias, SomSammm",
    "isMod": true,
    "isVIP": false
  },
  {
    "date": "13/01/2024",
    "time": "01:08:42",
    "username": "lakatastrauf",
    "message": "mais comment ils ont su que vous faisiez sa",
    "isMod": false,
    "isVIP": false
  },
  {
    "date": "13/01/2024",
    "time": "01:10:42",
    "username": "kgekraa",
    "message": "bientôt le week-end 😭",
    "isMod": true,
    "isVIP": false
  },
  {
    "date": "13/01/2024",
    "time": "01:10:48",
    "username": "kgekraa",
    "message": "j’en peux plus",
    "isMod": true,
    "isVIP": false
  },
  {
    "date": "13/01/2024",
    "time": "01:11:01",
    "username": "mystgun87",
    "message": "maintenant avc les Backup avc un pourcentage",
    "isMod": false,
    "isVIP": false
  },
  {
    "date": "13/01/2024",
    "time": "01:13:23",
    "username": "sne4kf4s7",
    "message": "Prénom: BOn. Nom: Toutou",
    "isMod": false,
    "isVIP": false
  },
  {
    "date": "13/01/2024",
    "time": "01:14:33",
    "username": "cheb_effeeeezz",
    "message": "tu la passer",
    "isMod": false,
    "isVIP": false
  },
  {
    "date": "13/01/2024",
    "time": "01:17:17",
    "username": "kgekraa",
    "message": "ah",
    "isMod": true,
    "isVIP": false
  },
  {
    "date": "13/01/2024",
    "time": "01:17:20",
    "username": "kgekraa",
    "message": "…",
    "isMod": true,
    "isVIP": false
  },
  {
    "date": "13/01/2024",
    "time": "01:17:44",
    "username": "kgekraa",
    "message": "faut arrêter de prendre les blague dans le chat elle sont pas forcément bonne",
    "isMod": true,
    "isVIP": false
  },
  {
    "date": "13/01/2024",
    "time": "01:17:44",
    "username": "mystgun87",
    "message": "lzriseAbadakor lzriseAbadakor lzriseAbadakor",
    "isMod": false,
    "isVIP": false
  },
  {
    "date": "13/01/2024",
    "time": "01:20:18",
    "username": "cheb_effeeeezz",
    "message": "les grainne",
    "isMod": false,
    "isVIP": false
  },
  {
    "date": "13/01/2024",
    "time": "01:31:21",
    "username": "jl_lucas08",
    "message": "En vrai faut qu'il défende les 4 il est chaud",
    "isMod": false,
    "isVIP": false
  },
  {
    "date": "13/01/2024",
    "time": "01:40:58",
    "username": "tilian00",
    "message": "Faudrait que tu arrives à lui parler pour lui dire que tu les(les afro) a vu et que tu la appelé pour t'aider a surveiller",
    "isMod": false,
    "isVIP": false
  },
  {
    "date": "13/01/2024",
    "time": "01:41:03",
    "username": "cheb_effeeeezz",
    "message": "car la defense étais bonne la",
    "isMod": false,
    "isVIP": false
  },
  {
    "date": "13/01/2024",
    "time": "01:41:28",
    "username": "cheb_effeeeezz",
    "message": "dommage qu’il prenne pas l’avocat",
    "isMod": false,
    "isVIP": false
  },
  {
    "date": "13/01/2024",
    "time": "01:50:01",
    "username": "wizebot",
    "message": "👤 Nouveau FOLLOW(S) ❤ theoo2810 ❤, BIENVENUE! (41178 followers) (+17).",
    "isMod": true,
    "isVIP": false
  },
  {
    "date": "13/01/2024",
    "time": "01:56:06",
    "username": "nassssma",
    "message": "perso!",
    "isMod": false,
    "isVIP": false
  },
  {
    "date": "13/01/2024",
    "time": "01:56:21",
    "username": "nassssma",
    "message": "!perso",
    "isMod": false,
    "isVIP": false
  },
  {
    "date": "13/01/2024",
    "time": "01:56:21",
    "username": "streamelements",
    "message": "Joshua Munoz 26 ans Grand de la Puente 13",
    "isMod": true,
    "isVIP": false
  },
  {
    "date": "13/01/2024",
    "time": "01:56:22",
    "username": "wizebot",
    "message": "Joshua Munoz 26 ans Grand de la Puente 13",
    "isMod": true,
    "isVIP": false
  },
  {
    "date": "13/01/2024",
    "time": "01:59:18",
    "username": "billow_tv",
    "message": "Comment va L'bonvieux",
    "isMod": false,
    "isVIP": false
  },
  {
    "date": "13/01/2024",
    "time": "02:00:23",
    "username": "billow_tv",
    "message": "trql",
    "isMod": false,
    "isVIP": false
  },
  {
    "date": "13/01/2024",
    "time": "02:00:43",
    "username": "wizebot",
    "message": "👤 Nouveau FOLLOW(S) ❤ Lokiii42 ❤, BIENVENUE! (41179 followers) (+18).",
    "isMod": true,
    "isVIP": false
  },
  {
    "date": "13/01/2024",
    "time": "02:00:43",
    "username": "lokiii42",
    "message": "MAIS MDRRR C TOI MUNOZ, je cherchais ton discord j'vois c'est toi",
    "isMod": false,
    "isVIP": false
  },
  {
    "date": "13/01/2024",
    "time": "02:01:14",
    "username": "cricrilost",
    "message": "sa va ou quoiiiiii",
    "isMod": false,
    "isVIP": false
  },
  {
    "date": "13/01/2024",
    "time": "02:02:04",
    "username": "lokiii42",
    "message": "Ils sont même pas près je vais les choquer sur la plaidoirie",
    "isMod": false,
    "isVIP": false
  },
  {
    "date": "13/01/2024",
    "time": "02:02:05",
    "username": "cricrilost",
    "message": "trkl",
    "isMod": false,
    "isVIP": false
  },
  {
    "date": "13/01/2024",
    "time": "02:02:44",
    "username": "lokiii42",
    "message": "MAIS MDRRRRR C TROP",
    "isMod": false,
    "isVIP": false
  },
  {
    "date": "13/01/2024",
    "time": "02:59:01",
    "username": "fda_delta",
    "message": "le retour de la caf encore 😂😂",
    "isMod": false,
    "isVIP": false
  }
]